factory_ai/__init__.py
factory_ai/bayesian_opt.py
factory_ai-0.1.0.dist-info/WHEEL
factory_ai-0.1.0.dist-info/METADATA
factory_ai-0.1.0.dist-info/RECORD
